reasoning/__init__.py
reasoning/core.py
reasoning/examples/anthropic_example.py
reasoning/examples/openai_example.py
reasoning/examples/openrouter_example.py
reasoning-0.1.0.dist-info/METADATA
reasoning-0.1.0.dist-info/WHEEL
reasoning-0.1.0.dist-info/RECORD
