Metadata-Version: 2.1
Name: reasoning
Version: 0.1.0
Summary: A reasoning framework for all LLMs
Home-page: https://github.com/colesmcintosh/reasoning
License: MIT
Keywords: llm,ai,reasoning,framework,openai,anthropic
Author: colesmcintosh
Author-email: colemcintosh6@gmail.com
Requires-Python: >=3.9
Classifier: Development Status :: 4 - Beta
Classifier: Intended Audience :: Developers
Classifier: License :: OSI Approved :: MIT License
Classifier: Programming Language :: Python :: 3
Classifier: Programming Language :: Python :: 3.9
Classifier: Programming Language :: Python :: 3.10
Classifier: Programming Language :: Python :: 3.11
Classifier: Programming Language :: Python :: 3.12
Classifier: Programming Language :: Python :: 3.13
Classifier: Topic :: Scientific/Engineering :: Artificial Intelligence
Classifier: Topic :: Software Development :: Libraries :: Python Modules
Requires-Dist: anthropic (>=0.45.2,<0.46.0)
Requires-Dist: openai (>=1.61.0,<2.0.0)
Requires-Dist: pydantic (>=2.6.1,<3.0.0)
Requires-Dist: python-dotenv (>=1.0.1,<2.0.0)
Requires-Dist: requests (>=2.31.0,<3.0.0)
Requires-Dist: typing-extensions (>=4.9.0,<5.0.0)
Project-URL: Documentation, https://github.com/colesmcintosh/reasoning
Project-URL: Repository, https://github.com/colesmcintosh/reasoning
